LICENSE
README.md
setup.py
truthometer/__init__.py
truthometer/correction_in_web_browser_opener.py
truthometer/entity_extractor.py
truthometer/fact_checker_via_web.py
truthometer/key_manager.py
truthometer/paragraph_comparer.py
truthometer/phrase_enumeration_manager.py
truthometer/regulations_corrector.py
truthometer/streamlit_runner.py
truthometer.egg-info/PKG-INFO
truthometer.egg-info/SOURCES.txt
truthometer.egg-info/dependency_links.txt
truthometer.egg-info/requires.txt
truthometer.egg-info/top_level.txt
truthometer/external_apis/__init__.py
truthometer/external_apis/bing_searcher.py
truthometer/external_apis/chat_gpt_api.py
truthometer/external_apis/google_know_graph_api.py
truthometer/external_apis/google_searcher.py
truthometer/external_apis/google_serp_searcher.py
truthometer/external_apis/openai_api_manager.py
truthometer/external_apis/wolfram_alpha_api.py
truthometer/external_apis/youtube_searcher.py
truthometer/html/__init__.py
truthometer/html/verification_page_builder.py
truthometer/integration/__init__.py
truthometer/integration/direct_fact_checker.py
truthometer/integration/gpt_telegram.py
truthometer/nlp_utils/__init__.py
truthometer/nlp_utils/noun_phrase_processor.py
truthometer/nlp_utils/string_distance_measurer.py
truthometer/nlp_utils/test_string_distance_measurer.py
truthometer/nlp_utils/verb_phrase_processor.py
truthometer/nlp_utils/allow_list_manager/__init__.py
truthometer/nlp_utils/allow_list_manager/allow_list_manager.py
truthometer/nlp_utils/allow_list_manager/resources/__init__.py
truthometer/nlp_utils/allow_list_manager/resources/abstract_noun.txt
truthometer/nlp_utils/allow_list_manager/resources/english_words10000.txt
truthometer/nlp_utils/allow_list_manager/resources/last_names.txt
truthometer/nlp_utils/allow_list_manager/resources/positive-words.txt
truthometer/nlp_utils/allow_list_manager/resources/positive_adjective_addit.txt
truthometer/nlp_utils/allow_list_manager/resources/pronouns_full.txt
truthometer/nlp_utils/ner/__init__.py
truthometer/nlp_utils/ner/named_entity_recognizer.py
truthometer/third_party_models/__init__.py
truthometer/third_party_models/chat_gpt_answer_format_adapter.py
truthometer/truthometer.egg-info/SOURCES.txt
truthometer/truthometer.egg-info/dependency_links.txt
truthometer/truthometer.egg-info/requires.txt
truthometer/truthometer.egg-info/top_level.txt