Metadata-Version: 2.1
Name: truthometer
Version: 0.1.16
Summary: Fact checker for GPT and other LLMs
Home-page: https://github.com/bgalitsky/Truth-O-Meter-Making-ChatGPT-Truthful
Author: Boris Galitsky
Author-email: bgalitsky@hotmail.com
License: BSD 2-clause
Classifier: Intended Audience :: Science/Research
Classifier: License :: OSI Approved :: BSD License
Classifier: Operating System :: POSIX :: Linux
Classifier: Programming Language :: Python :: 3.9
License-File: LICENSE
